odoo/addons/website_sale_delivery_group/README.rst
odoo/addons/website_sale_delivery_group/__init__.py
odoo/addons/website_sale_delivery_group/__manifest__.py
odoo/addons/website_sale_delivery_group/demo/demo.xml
odoo/addons/website_sale_delivery_group/i18n/es_AR.po
odoo/addons/website_sale_delivery_group/i18n/website_sale_delivery_group.pot
odoo/addons/website_sale_delivery_group/models/__init__.py
odoo/addons/website_sale_delivery_group/models/delivery_carrier_group.py
odoo/addons/website_sale_delivery_group/readme/CONFIGURE.rst
odoo/addons/website_sale_delivery_group/readme/CONTRIBUTORS.rst
odoo/addons/website_sale_delivery_group/readme/DESCRIPTION.rst
odoo/addons/website_sale_delivery_group/security/ir.model.access.csv
odoo/addons/website_sale_delivery_group/static/description/icon.png
odoo/addons/website_sale_delivery_group/static/description/index.html
odoo/addons/website_sale_delivery_group/static/description/website_sale_delivery_group_1.png
odoo/addons/website_sale_delivery_group/static/description/website_sale_delivery_group_2.png
odoo/addons/website_sale_delivery_group/views/delivery_carrier.xml
odoo/addons/website_sale_delivery_group/views/delivery_carrier_group.xml
odoo/addons/website_sale_delivery_group/views/templates.xml
odoo14_addon_website_sale_delivery_group-14.0.1.0.1.dist-info/METADATA
odoo14_addon_website_sale_delivery_group-14.0.1.0.1.dist-info/WHEEL
odoo14_addon_website_sale_delivery_group-14.0.1.0.1.dist-info/top_level.txt
odoo14_addon_website_sale_delivery_group-14.0.1.0.1.dist-info/RECORD
